diana/__init__.py
diana/injector.py
diana/module.py
diana/util.py
diana-3.1.2.dist-info/LICENSE
diana-3.1.2.dist-info/METADATA
diana-3.1.2.dist-info/WHEEL
diana-3.1.2.dist-info/top_level.txt
diana-3.1.2.dist-info/RECORD
