Metadata-Version: 2.1
Name: diana
Version: 3.1.2
Summary: Simple Dependency Injector for python
Home-page: http://github.com/xlevus/python-diana
Author: Chris Targett
Author-email: chris@xlevus.net
License: MIT
Platform: UNKNOWN
Classifier: Development Status :: 4 - Beta
Classifier: Intended Audience :: Developers
Classifier: License :: OSI Approved :: MIT License
Classifier: Programming Language :: Python :: 3.7
Classifier: Programming Language :: Python :: 3.8
Requires-Python: >3.6.*, <4
